{
  "items": [
    {
      "id": 1,
      "name": "Apple Watch Gen 3",
      "description": "Description of Item 1",
      "price": 10.89,
      "image": "item1.jpg",
      "address": "123 Main St",
      "icon": "./public/images/1.png"
    },
    {
      "id": 2,
      "name": "Item 2",
      "description": "New Description of Item 2",
      "price": 17.99,
      "image": "item2.jpg",
      "address": "46 Elm St",
      "type": "home"
    },
    {
      "name": "Item 3",
      "description": "Description of Item 3",
      "price": "12.99",
      "image": "item3.jpg",
      "address": "987 Elmo St",
      "user_id": 3,
      "id": 3
    },
    {
      "name": "Item 4",
      "description": "This is Item 4, a high-quality product designed to meet your needs.",
      "price": "15.95",
      "image": "item4.jpg",
      "address": "1234 Maple Ave",
      "user_id": 4,
      "id": 4
    },
    {
      "name": "Cappuccino",
      "description": "Coffee",
      "price": "5",
      "image": "coffee.png",
      "address": "Shop",
      "user_id": 1,
      "id": 7
    },
    {
      "name": "Item 18",
      "description": "Lots",
      "price": "59",
      "image": "item.jpg",
      "address": "1600 Pennsylvania Ave NW, Washington, DC 20006",
      "user_id": 2,
      "id": 8
    },
    {
      "name": "Banana",
      "description": "Yellow",
      "price": "7",
      "image": "image.jpg",
      "address": "Piazza del Duomo - 56126 Pisa (PI)",
      "user_id": 2,
      "id": 9
    }
  ],
  "users": [
    {
      "email": "test@example.com",
      "password": "$2a$10$JKhtuUOALTTVludrzxDBduVk8hT9TsaCApq33waHAwu7Wd165EwLy",
      "fullName": "John Doe",
      "phoneNumber": "1234567890",
      "id": 1
    },
    {
      "email": "test2@example.com",
      "password": "$2a$10$WyyI0zXgpMio8BF76Tu8s.eKc8SThYTLDf708XvjfwnT50TOUZ.zW",
      "fullName": "John Two",
      "phoneNumber": "1234567890",
      "id": 2
    },
    {
      "email": "admin@gmail.com",
      "password": "$2a$10$MdoNy8.0GL/M5KYsMDF2POvS1/6FT5/6QCVb1aMeqBaT3X0ydhs2e",
      "fullName": "admin",
      "phoneNumber": "12345",
      "id": 3
    },
    {
      "email": "New@gmail.com",
      "password": "$2a$10$uwMBkan.SyO1JH.BkvwuUeYH.y0K/bv6.CAnqBBQgCHOqdMB6H7VC",
      "fullName": "New User",
      "phoneNumber": "123456",
      "id": 4
    }
  ]
}